whispercpp-0.0.17.dist-info/METADATA
whispercpp-0.0.17.dist-info/RECORD
whispercpp-0.0.17.dist-info/WHEEL
whispercpp/__init__.py
whispercpp/__init__.pyi
whispercpp/api.pyi
whispercpp/api_cpp2py_export.so
whispercpp/audio.pyi
whispercpp/audio_cpp2py_export.so
whispercpp/utils.py
